main.py
dkt-0.0.1.dist-info/METADATA
dkt-0.0.1.dist-info/WHEEL
dkt-0.0.1.dist-info/top_level.txt
dkt-0.0.1.dist-info/RECORD
