Metadata-Version: 2.1
Name: dkt
Version: 0.0.1
Summary: dkt
Author: 4sushi
License: MIT
Keywords: dkt
Platform: UNKNOWN
Classifier: Programming Language :: Python :: 3
Classifier: License :: OSI Approved :: MIT License
Classifier: Operating System :: OS Independent
Requires-Python: >=3.7
